[{"timestamp":"2024-01-01T04:37:00.414Z","count":0,"uniques":0},{"timestamp":"2024-02-01T04:37:00.414Z","count":0,"uniques":0},{"timestamp":"2024-03-01T04:37:00.414Z","count":0,"uniques":0},{"timestamp":"2024-04-01T06:14:14.608Z","count":10,"uniques":5},{"timestamp":"2024-05-01T00:37:53.320Z","count":53,"uniques":18},{"timestamp":"2024-06-01T00:40:34.653Z","count":130,"uniques":24},{"timestamp":"2024-07-01T18:16:35.785Z","count":85,"uniques":24},{"timestamp":"2024-08-01T06:18:53.284Z","count":38,"uniques":17},{"timestamp":"2024-09-01T12:22:50.756Z","count":44,"uniques":18},{"timestamp":"2024-10-01T12:23:23.539Z","count":37,"uniques":25},{"timestamp":"2024-11-01T12:21:50.992Z","count":49,"uniques":25},{"timestamp":"2024-12-01T06:21:44.064Z","count":44,"uniques":20},{"timestamp":"2025-01-01T00:46:13.201Z","count":44,"uniques":20}]
