[{"timestamp":"2024-08-13T00:46:09.769Z","count":0,"uniques":0},{"timestamp":"2024-08-14T00:43:48.809Z","count":0,"uniques":0},{"timestamp":"2024-08-15T00:42:22.285Z","count":0,"uniques":0},{"timestamp":"2024-08-16T00:44:52.363Z","count":0,"uniques":0},{"timestamp":"2024-08-17T00:43:07.931Z","count":0,"uniques":0},{"timestamp":"2024-08-18T00:47:52.826Z","count":0,"uniques":0},{"timestamp":"2024-08-19T00:44:49.001Z","count":0,"uniques":0},{"timestamp":"2024-08-20T00:43:58.122Z","count":0,"uniques":0}]
