[{"timestamp":"2025-07-17T01:00:21.234Z","count":0,"uniques":0},{"timestamp":"2025-07-18T00:59:13.256Z","count":0,"uniques":0},{"timestamp":"2025-07-19T00:57:46.077Z","count":0,"uniques":0},{"timestamp":"2025-07-20T01:05:22.071Z","count":0,"uniques":0},{"timestamp":"2025-07-21T01:03:29.316Z","count":0,"uniques":0},{"timestamp":"2025-07-22T01:00:12.446Z","count":0,"uniques":0},{"timestamp":"2025-07-23T01:00:39.855Z","count":0,"uniques":0},{"timestamp":"2025-07-24T01:00:05.308Z","count":0,"uniques":0}]
