[{"timestamp":"2025-07-01T01:05:18.703Z","count":0,"uniques":0},{"timestamp":"2025-07-02T00:56:22.715Z","count":0,"uniques":0},{"timestamp":"2025-07-03T00:56:45.761Z","count":0,"uniques":0},{"timestamp":"2025-07-04T00:57:07.510Z","count":0,"uniques":0},{"timestamp":"2025-07-05T00:55:27.054Z","count":0,"uniques":0},{"timestamp":"2025-07-06T01:02:48.911Z","count":0,"uniques":0},{"timestamp":"2025-07-07T01:01:36.115Z","count":0,"uniques":0},{"timestamp":"2025-07-08T00:56:58.369Z","count":0,"uniques":0}]
