[{"timestamp":"2025-05-04T12:25:32.730Z","count":0,"uniques":0},{"timestamp":"2025-05-05T12:25:32.730Z","count":0,"uniques":0},{"timestamp":"2025-05-06T12:25:32.730Z","count":0,"uniques":0},{"timestamp":"2025-05-07T12:25:32.730Z","count":0,"uniques":0},{"timestamp":"2025-05-08T12:25:32.730Z","count":0,"uniques":0},{"timestamp":"2025-05-09T12:25:32.730Z","count":0,"uniques":0},{"timestamp":"2025-05-10T12:25:32.730Z","count":0,"uniques":0},{"timestamp":"2025-05-11T00:59:08.612Z","count":0,"uniques":0}]
