[{"timestamp":"2026-01-26T01:07:21.961Z","count":0,"uniques":0},{"timestamp":"2026-01-27T01:06:35.136Z","count":0,"uniques":0},{"timestamp":"2026-01-28T01:03:16.935Z","count":0,"uniques":0},{"timestamp":"2026-01-29T01:11:36.539Z","count":0,"uniques":0},{"timestamp":"2026-01-30T01:09:43.539Z","count":0,"uniques":0},{"timestamp":"2026-01-31T01:08:31.324Z","count":0,"uniques":0},{"timestamp":"2026-02-01T01:21:23.068Z","count":0,"uniques":0},{"timestamp":"2026-02-02T01:14:15.043Z","count":0,"uniques":0},{"timestamp":"2026-02-03T01:14:59.908Z","count":0,"uniques":0},{"timestamp":"2026-02-04T06:46:31.220Z","count":0,"uniques":0},{"timestamp":"2026-02-05T01:12:23.411Z","count":0,"uniques":0},{"timestamp":"2026-02-06T01:10:37.457Z","count":0,"uniques":0},{"timestamp":"2026-02-07T01:08:46.659Z","count":0,"uniques":0},{"timestamp":"2026-02-08T01:30:23.303Z","count":0,"uniques":0},{"timestamp":"2026-02-09T01:17:03.622Z","count":0,"uniques":0},{"timestamp":"2026-02-10T01:24:46.058Z","count":0,"uniques":0},{"timestamp":"2026-02-11T01:23:39.981Z","count":0,"uniques":0},{"timestamp":"2026-02-12T01:15:37.239Z","count":0,"uniques":0},{"timestamp":"2026-02-13T01:19:30.346Z","count":0,"uniques":0},{"timestamp":"2026-02-14T01:11:00.030Z","count":0,"uniques":0},{"timestamp":"2026-02-15T01:18:13.662Z","count":0,"uniques":0},{"timestamp":"2026-02-16T01:16:18.557Z","count":0,"uniques":0},{"timestamp":"2026-02-17T01:14:23.607Z","count":0,"uniques":0},{"timestamp":"2026-02-18T01:16:33.861Z","count":0,"uniques":0},{"timestamp":"2026-02-19T01:15:43.709Z","count":0,"uniques":0},{"timestamp":"2026-02-20T01:11:22.255Z","count":0,"uniques":0},{"timestamp":"2026-02-21T01:10:57.629Z","count":0,"uniques":0},{"timestamp":"2026-02-22T01:14:47.599Z","count":0,"uniques":0},{"timestamp":"2026-02-23T01:14:27.708Z","count":0,"uniques":0},{"timestamp":"2026-02-24T01:13:43.308Z","count":0,"uniques":0},{"timestamp":"2026-02-25T01:17:21.295Z","count":0,"uniques":0}]
