[{"timestamp":"2025-09-04T00:52:27.362Z","count":0,"uniques":0},{"timestamp":"2025-09-05T00:53:39.756Z","count":0,"uniques":0},{"timestamp":"2025-09-06T00:51:58.797Z","count":0,"uniques":0},{"timestamp":"2025-09-07T00:57:33.145Z","count":0,"uniques":0},{"timestamp":"2025-09-08T00:56:21.318Z","count":0,"uniques":0},{"timestamp":"2025-09-09T00:54:45.312Z","count":0,"uniques":0},{"timestamp":"2025-09-10T00:53:20.322Z","count":0,"uniques":0},{"timestamp":"2025-09-11T00:53:42.241Z","count":0,"uniques":0}]
