[{"timestamp":"2025-08-05T01:04:14.549Z","count":0,"uniques":0},{"timestamp":"2025-08-06T01:03:23.959Z","count":0,"uniques":0},{"timestamp":"2025-08-07T01:03:40.364Z","count":0,"uniques":0},{"timestamp":"2025-08-08T01:03:27.472Z","count":0,"uniques":0},{"timestamp":"2025-08-09T00:57:09.912Z","count":0,"uniques":0},{"timestamp":"2025-08-10T01:06:47.221Z","count":0,"uniques":0},{"timestamp":"2025-08-11T01:04:50.119Z","count":0,"uniques":0},{"timestamp":"2025-08-12T00:57:39.232Z","count":0,"uniques":0}]
