[{"timestamp":"2026-01-31T01:00:38.986Z","count":0,"uniques":0},{"timestamp":"2026-02-01T00:00:00.000Z","count":5,"uniques":3},{"timestamp":"2026-02-02T01:06:21.355Z","count":0,"uniques":0},{"timestamp":"2026-02-03T01:07:13.042Z","count":0,"uniques":0},{"timestamp":"2026-02-04T00:00:00.000Z","count":1,"uniques":1},{"timestamp":"2026-02-05T01:04:50.731Z","count":0,"uniques":0},{"timestamp":"2026-02-06T01:02:53.361Z","count":0,"uniques":0},{"timestamp":"2026-02-07T01:01:26.945Z","count":0,"uniques":0}]
