[{"timestamp":"2025-12-29T06:28:11.624Z","count":0,"uniques":0},{"timestamp":"2025-12-30T00:59:06.325Z","count":0,"uniques":0},{"timestamp":"2025-12-31T01:00:46.199Z","count":0,"uniques":0},{"timestamp":"2026-01-01T01:05:34.596Z","count":0,"uniques":0},{"timestamp":"2026-01-02T01:00:24.362Z","count":0,"uniques":0},{"timestamp":"2026-01-03T00:55:49.308Z","count":0,"uniques":0},{"timestamp":"2026-01-04T01:06:34.837Z","count":0,"uniques":0},{"timestamp":"2026-01-05T01:05:05.511Z","count":0,"uniques":0}]
