[{"timestamp":"2024-06-06T00:39:51.225Z","count":0,"uniques":0},{"timestamp":"2024-06-07T00:40:33.905Z","count":0,"uniques":0},{"timestamp":"2024-06-08T00:40:22.181Z","count":0,"uniques":0},{"timestamp":"2024-06-09T00:43:56.264Z","count":0,"uniques":0},{"timestamp":"2024-06-10T00:41:51.137Z","count":0,"uniques":0},{"timestamp":"2024-06-11T00:39:59.217Z","count":0,"uniques":0},{"timestamp":"2024-06-12T00:40:09.651Z","count":0,"uniques":0},{"timestamp":"2024-06-13T00:40:38.037Z","count":0,"uniques":0},{"timestamp":"2024-06-14T00:40:10.241Z","count":0,"uniques":0},{"timestamp":"2024-06-15T00:39:52.826Z","count":0,"uniques":0},{"timestamp":"2024-06-16T00:44:26.391Z","count":0,"uniques":0},{"timestamp":"2024-06-17T00:42:47.244Z","count":0,"uniques":0},{"timestamp":"2024-06-18T00:41:42.860Z","count":0,"uniques":0},{"timestamp":"2024-06-19T00:00:00.000Z","count":11,"uniques":1},{"timestamp":"2024-06-20T00:39:34.833Z","count":0,"uniques":0},{"timestamp":"2024-06-21T00:40:50.056Z","count":0,"uniques":0},{"timestamp":"2024-06-22T00:00:00.000Z","count":1,"uniques":1},{"timestamp":"2024-06-23T00:43:03.327Z","count":0,"uniques":0},{"timestamp":"2024-06-24T00:42:50.552Z","count":0,"uniques":0},{"timestamp":"2024-06-25T00:00:00.000Z","count":15,"uniques":1},{"timestamp":"2024-06-26T00:40:59.348Z","count":0,"uniques":0},{"timestamp":"2024-06-27T00:40:39.945Z","count":0,"uniques":0},{"timestamp":"2024-06-28T00:41:48.087Z","count":0,"uniques":0},{"timestamp":"2024-06-29T00:40:19.680Z","count":0,"uniques":0},{"timestamp":"2024-06-30T00:44:48.793Z","count":0,"uniques":0},{"timestamp":"2024-07-01T00:45:50.789Z","count":0,"uniques":0},{"timestamp":"2024-07-02T00:00:00.000Z","count":1,"uniques":1},{"timestamp":"2024-07-03T00:41:58.005Z","count":0,"uniques":0},{"timestamp":"2024-07-04T00:00:00.000Z","count":18,"uniques":2},{"timestamp":"2024-07-05T00:42:06.299Z","count":0,"uniques":0},{"timestamp":"2024-07-06T00:39:53.057Z","count":0,"uniques":0}]
