[{"timestamp":"2024-09-01T00:52:10.117Z","count":0,"uniques":0},{"timestamp":"2024-09-02T00:46:47.650Z","count":0,"uniques":0},{"timestamp":"2024-09-03T00:44:54.712Z","count":0,"uniques":0},{"timestamp":"2024-09-04T00:45:14.080Z","count":0,"uniques":0},{"timestamp":"2024-09-05T00:46:18.696Z","count":0,"uniques":0},{"timestamp":"2024-09-06T00:46:18.153Z","count":0,"uniques":0},{"timestamp":"2024-09-07T00:44:42.083Z","count":0,"uniques":0},{"timestamp":"2024-09-08T00:49:15.056Z","count":0,"uniques":0}]
