[{"timestamp":"2026-05-29T01:59:17.851Z","count":0,"uniques":0},{"timestamp":"2026-05-30T00:00:00.000Z","count":3,"uniques":2},{"timestamp":"2026-05-31T02:08:08.308Z","count":0,"uniques":0},{"timestamp":"2026-06-01T02:17:24.298Z","count":0,"uniques":0},{"timestamp":"2026-06-02T02:17:55.471Z","count":0,"uniques":0},{"timestamp":"2026-06-03T02:35:54.221Z","count":0,"uniques":0},{"timestamp":"2026-06-04T00:00:00.000Z","count":4,"uniques":2},{"timestamp":"2026-06-05T02:06:40.450Z","count":0,"uniques":0}]
