[{"timestamp":"2025-07-21T00:59:01.237Z","count":0,"uniques":0},{"timestamp":"2025-07-22T00:55:39.318Z","count":0,"uniques":0},{"timestamp":"2025-07-23T00:56:17.672Z","count":0,"uniques":0},{"timestamp":"2025-07-24T00:55:36.868Z","count":0,"uniques":0},{"timestamp":"2025-07-25T00:55:44.755Z","count":0,"uniques":0},{"timestamp":"2025-07-26T00:53:50.387Z","count":0,"uniques":0},{"timestamp":"2025-07-27T01:00:51.606Z","count":0,"uniques":0},{"timestamp":"2025-07-28T00:59:51.582Z","count":0,"uniques":0},{"timestamp":"2025-07-29T01:01:04.466Z","count":0,"uniques":0},{"timestamp":"2025-07-30T00:56:50.082Z","count":0,"uniques":0},{"timestamp":"2025-07-31T00:57:08.127Z","count":0,"uniques":0},{"timestamp":"2025-08-01T01:02:54.931Z","count":0,"uniques":0},{"timestamp":"2025-08-02T00:53:32.676Z","count":0,"uniques":0},{"timestamp":"2025-08-03T01:02:05.799Z","count":0,"uniques":0},{"timestamp":"2025-08-04T01:01:02.614Z","count":0,"uniques":0},{"timestamp":"2025-08-05T00:57:53.883Z","count":0,"uniques":0},{"timestamp":"2025-08-06T00:57:03.337Z","count":0,"uniques":0},{"timestamp":"2025-08-07T00:57:27.950Z","count":0,"uniques":0},{"timestamp":"2025-08-08T00:57:13.674Z","count":0,"uniques":0},{"timestamp":"2025-08-09T00:50:56.475Z","count":0,"uniques":0},{"timestamp":"2025-08-10T01:00:24.357Z","count":0,"uniques":0},{"timestamp":"2025-08-11T00:58:28.396Z","count":0,"uniques":0},{"timestamp":"2025-08-12T00:51:32.969Z","count":0,"uniques":0},{"timestamp":"2025-08-13T00:52:49.542Z","count":0,"uniques":0},{"timestamp":"2025-08-14T00:52:40.549Z","count":0,"uniques":0},{"timestamp":"2025-08-15T00:53:30.122Z","count":0,"uniques":0},{"timestamp":"2025-08-16T00:49:30.209Z","count":0,"uniques":0},{"timestamp":"2025-08-17T00:57:44.227Z","count":0,"uniques":0},{"timestamp":"2025-08-18T00:57:22.151Z","count":0,"uniques":0},{"timestamp":"2025-08-19T00:50:30.908Z","count":0,"uniques":0},{"timestamp":"2025-08-20T00:48:40.862Z","count":0,"uniques":0}]
