[{"timestamp":"2024-07-04T00:00:00.000Z","count":7,"uniques":1},{"timestamp":"2024-07-05T00:00:00.000Z","count":29,"uniques":1},{"timestamp":"2024-07-06T00:35:02.174Z","count":0,"uniques":0},{"timestamp":"2024-07-07T00:40:23.594Z","count":0,"uniques":0},{"timestamp":"2024-07-08T00:38:00.621Z","count":0,"uniques":0},{"timestamp":"2024-07-09T00:36:38.436Z","count":0,"uniques":0},{"timestamp":"2024-07-10T00:37:49.018Z","count":0,"uniques":0},{"timestamp":"2024-07-11T00:37:38.639Z","count":0,"uniques":0}]
