[{"timestamp":"2025-10-24T00:45:35.694Z","count":0,"uniques":0},{"timestamp":"2025-10-25T00:48:05.761Z","count":0,"uniques":0},{"timestamp":"2025-10-26T00:52:15.279Z","count":0,"uniques":0},{"timestamp":"2025-10-27T00:54:35.894Z","count":0,"uniques":0},{"timestamp":"2025-10-28T00:48:08.686Z","count":0,"uniques":0},{"timestamp":"2025-10-29T00:51:30.918Z","count":0,"uniques":0},{"timestamp":"2025-10-30T00:50:49.997Z","count":0,"uniques":0},{"timestamp":"2025-10-31T00:49:15.201Z","count":0,"uniques":0}]
