[{"timestamp":"2025-03-19T00:43:43.696Z","count":0,"uniques":0},{"timestamp":"2025-03-20T00:43:08.793Z","count":0,"uniques":0},{"timestamp":"2025-03-21T00:44:23.419Z","count":0,"uniques":0},{"timestamp":"2025-03-22T00:42:26.776Z","count":0,"uniques":0},{"timestamp":"2025-03-23T00:47:35.962Z","count":0,"uniques":0},{"timestamp":"2025-03-24T00:45:36.596Z","count":0,"uniques":0},{"timestamp":"2025-03-25T00:00:00.000Z","count":4,"uniques":2},{"timestamp":"2025-03-26T00:44:01.200Z","count":0,"uniques":0}]
