[{"timestamp":"2024-12-05T00:51:57.204Z","count":0,"uniques":0},{"timestamp":"2024-12-06T00:51:20.259Z","count":0,"uniques":0},{"timestamp":"2024-12-07T00:50:04.041Z","count":0,"uniques":0},{"timestamp":"2024-12-08T00:54:47.555Z","count":0,"uniques":0},{"timestamp":"2024-12-09T00:52:53.446Z","count":0,"uniques":0},{"timestamp":"2024-12-10T00:51:53.999Z","count":0,"uniques":0},{"timestamp":"2024-12-11T00:51:01.032Z","count":0,"uniques":0},{"timestamp":"2024-12-12T00:50:56.408Z","count":0,"uniques":0}]
