[{"timestamp":"2026-03-27T01:09:46.096Z","count":0,"uniques":0},{"timestamp":"2026-03-28T01:04:05.406Z","count":0,"uniques":0},{"timestamp":"2026-03-29T01:13:09.119Z","count":0,"uniques":0},{"timestamp":"2026-03-30T01:13:48.387Z","count":0,"uniques":0},{"timestamp":"2026-03-31T01:11:39.059Z","count":0,"uniques":0},{"timestamp":"2026-04-01T01:18:18.201Z","count":0,"uniques":0},{"timestamp":"2026-04-02T01:08:38.446Z","count":0,"uniques":0},{"timestamp":"2026-04-03T01:11:37.465Z","count":0,"uniques":0}]
