[{"timestamp":"2025-09-27T00:51:00.865Z","count":0,"uniques":0},{"timestamp":"2025-09-28T00:58:40.379Z","count":0,"uniques":0},{"timestamp":"2025-09-29T00:54:50.078Z","count":0,"uniques":0},{"timestamp":"2025-09-30T00:53:46.411Z","count":0,"uniques":0},{"timestamp":"2025-10-01T00:59:33.751Z","count":0,"uniques":0},{"timestamp":"2025-10-02T00:51:47.275Z","count":0,"uniques":0},{"timestamp":"2025-10-03T00:52:27.846Z","count":0,"uniques":0},{"timestamp":"2025-10-04T00:50:32.306Z","count":0,"uniques":0}]
