[{"timestamp":"2024-12-26T00:49:09.628Z","count":0,"uniques":0},{"timestamp":"2024-12-27T00:49:06.019Z","count":0,"uniques":0},{"timestamp":"2024-12-28T00:48:41.290Z","count":0,"uniques":0},{"timestamp":"2024-12-29T00:53:31.826Z","count":0,"uniques":0},{"timestamp":"2024-12-30T00:51:17.524Z","count":0,"uniques":0},{"timestamp":"2024-12-31T00:49:01.395Z","count":0,"uniques":0},{"timestamp":"2025-01-01T00:54:35.837Z","count":0,"uniques":0},{"timestamp":"2025-01-02T00:50:39.421Z","count":0,"uniques":0}]
