[{"timestamp":"2025-03-22T00:51:06.314Z","count":0,"uniques":0},{"timestamp":"2025-03-23T00:57:24.848Z","count":0,"uniques":0},{"timestamp":"2025-03-24T00:54:18.328Z","count":0,"uniques":0},{"timestamp":"2025-03-25T00:54:23.303Z","count":0,"uniques":0},{"timestamp":"2025-03-26T00:53:41.607Z","count":0,"uniques":0},{"timestamp":"2025-03-27T00:53:35.816Z","count":0,"uniques":0},{"timestamp":"2025-03-28T00:52:25.710Z","count":0,"uniques":0},{"timestamp":"2025-03-29T00:52:31.537Z","count":0,"uniques":0}]
