[{"timestamp":"2026-05-24T02:04:07.804Z","count":0,"uniques":0},{"timestamp":"2026-05-25T02:10:05.264Z","count":0,"uniques":0},{"timestamp":"2026-05-26T00:00:00.000Z","count":1,"uniques":1},{"timestamp":"2026-05-27T02:10:36.776Z","count":0,"uniques":0},{"timestamp":"2026-05-28T01:54:01.136Z","count":0,"uniques":0},{"timestamp":"2026-05-29T00:00:00.000Z","count":1,"uniques":1},{"timestamp":"2026-05-30T01:58:58.746Z","count":0,"uniques":0},{"timestamp":"2026-05-31T02:11:48.030Z","count":0,"uniques":0}]
