[{"timestamp":"2024-11-01T00:42:22.999Z","count":0,"uniques":0},{"timestamp":"2024-11-02T00:37:38.339Z","count":0,"uniques":0},{"timestamp":"2024-11-03T00:41:59.152Z","count":0,"uniques":0},{"timestamp":"2024-11-04T00:40:07.013Z","count":0,"uniques":0},{"timestamp":"2024-11-05T00:37:45.231Z","count":0,"uniques":0},{"timestamp":"2024-11-06T00:37:40.738Z","count":0,"uniques":0},{"timestamp":"2024-11-07T00:37:53.598Z","count":0,"uniques":0},{"timestamp":"2024-11-08T00:37:40.031Z","count":0,"uniques":0}]
