[{"timestamp":"2025-09-13T00:38:59.108Z","count":0,"uniques":0},{"timestamp":"2025-09-14T00:00:00.000Z","count":14,"uniques":3},{"timestamp":"2025-09-15T00:45:23.015Z","count":0,"uniques":0},{"timestamp":"2025-09-16T00:41:00.859Z","count":0,"uniques":0},{"timestamp":"2025-09-17T00:41:35.969Z","count":0,"uniques":0},{"timestamp":"2025-09-18T00:41:13.869Z","count":0,"uniques":0},{"timestamp":"2025-09-19T00:43:09.424Z","count":0,"uniques":0},{"timestamp":"2025-09-20T00:40:12.166Z","count":0,"uniques":0}]
