[{"timestamp":"2025-01-31T00:38:50.410Z","count":0,"uniques":0},{"timestamp":"2025-02-01T00:41:34.691Z","count":0,"uniques":0},{"timestamp":"2025-02-02T00:41:19.370Z","count":0,"uniques":0},{"timestamp":"2025-02-03T00:40:09.680Z","count":0,"uniques":0},{"timestamp":"2025-02-04T00:38:55.083Z","count":0,"uniques":0},{"timestamp":"2025-02-05T00:39:13.671Z","count":0,"uniques":0},{"timestamp":"2025-02-06T00:39:21.735Z","count":0,"uniques":0},{"timestamp":"2025-02-07T00:39:24.320Z","count":0,"uniques":0}]
