[{"timestamp":"2025-04-12T00:46:43.946Z","count":0,"uniques":0},{"timestamp":"2025-04-13T02:14:37.912Z","count":0,"uniques":0},{"timestamp":"2025-04-14T00:50:16.107Z","count":0,"uniques":0},{"timestamp":"2025-04-15T00:49:18.413Z","count":0,"uniques":0},{"timestamp":"2025-04-16T12:19:51.700Z","count":0,"uniques":0},{"timestamp":"2025-04-17T12:19:51.700Z","count":0,"uniques":0},{"timestamp":"2025-04-18T12:19:51.700Z","count":0,"uniques":0},{"timestamp":"2025-04-19T12:19:51.700Z","count":0,"uniques":0},{"timestamp":"2025-04-20T12:19:51.700Z","count":0,"uniques":0},{"timestamp":"2025-04-21T12:19:51.700Z","count":0,"uniques":0},{"timestamp":"2025-04-22T12:19:51.700Z","count":0,"uniques":0},{"timestamp":"2025-04-23T12:19:51.700Z","count":0,"uniques":0},{"timestamp":"2025-04-24T12:19:51.700Z","count":0,"uniques":0},{"timestamp":"2025-04-25T12:19:51.700Z","count":0,"uniques":0},{"timestamp":"2025-04-26T12:19:51.700Z","count":0,"uniques":0},{"timestamp":"2025-04-27T12:19:51.700Z","count":0,"uniques":0},{"timestamp":"2025-04-28T12:19:51.700Z","count":0,"uniques":0},{"timestamp":"2025-04-29T12:19:51.700Z","count":0,"uniques":0},{"timestamp":"2025-04-30T12:19:51.700Z","count":0,"uniques":0},{"timestamp":"2025-05-01T12:19:51.700Z","count":0,"uniques":0},{"timestamp":"2025-05-02T12:19:51.700Z","count":0,"uniques":0},{"timestamp":"2025-05-03T12:19:51.700Z","count":0,"uniques":0},{"timestamp":"2025-05-04T00:00:00.000Z","count":6,"uniques":1},{"timestamp":"2025-05-05T00:00:00.000Z","count":2,"uniques":1},{"timestamp":"2025-05-06T12:19:51.700Z","count":0,"uniques":0},{"timestamp":"2025-05-07T12:19:51.700Z","count":0,"uniques":0},{"timestamp":"2025-05-08T12:19:51.700Z","count":0,"uniques":0},{"timestamp":"2025-05-09T12:19:51.700Z","count":0,"uniques":0},{"timestamp":"2025-05-10T12:19:51.700Z","count":0,"uniques":0},{"timestamp":"2025-05-11T00:00:00.000Z","count":2,"uniques":1},{"timestamp":"2025-05-12T00:52:50.222Z","count":0,"uniques":0}]
