[{"timestamp":"2026-04-06T01:19:33.301Z","count":0,"uniques":0},{"timestamp":"2026-04-07T01:17:00.017Z","count":0,"uniques":0},{"timestamp":"2026-04-08T01:18:18.510Z","count":0,"uniques":0},{"timestamp":"2026-04-09T01:07:48.327Z","count":0,"uniques":0},{"timestamp":"2026-04-10T01:19:23.263Z","count":0,"uniques":0},{"timestamp":"2026-04-11T01:14:08.943Z","count":0,"uniques":0},{"timestamp":"2026-04-12T01:23:26.665Z","count":0,"uniques":0},{"timestamp":"2026-04-13T01:24:23.863Z","count":0,"uniques":0}]
