[{"timestamp":"2025-11-12T00:53:00.323Z","count":0,"uniques":0},{"timestamp":"2025-11-13T00:53:41.476Z","count":0,"uniques":0},{"timestamp":"2025-11-14T00:52:45.602Z","count":0,"uniques":0},{"timestamp":"2025-11-15T00:52:05.456Z","count":0,"uniques":0},{"timestamp":"2025-11-16T00:57:30.354Z","count":0,"uniques":0},{"timestamp":"2025-11-17T00:55:18.971Z","count":0,"uniques":0},{"timestamp":"2025-11-18T00:52:27.270Z","count":0,"uniques":0},{"timestamp":"2025-11-19T00:53:22.238Z","count":0,"uniques":0}]
