[{"timestamp":"2025-03-14T00:48:06.739Z","count":0,"uniques":0},{"timestamp":"2025-03-15T00:47:49.420Z","count":0,"uniques":0},{"timestamp":"2025-03-16T00:51:57.572Z","count":0,"uniques":0},{"timestamp":"2025-03-17T00:50:27.052Z","count":0,"uniques":0},{"timestamp":"2025-03-18T00:48:43.035Z","count":0,"uniques":0},{"timestamp":"2025-03-19T00:48:53.987Z","count":0,"uniques":0},{"timestamp":"2025-03-20T00:48:23.542Z","count":0,"uniques":0},{"timestamp":"2025-03-21T00:50:09.728Z","count":0,"uniques":0}]
