[{"timestamp":"2023-06-01T04:35:25.542Z","count":0,"uniques":0},{"timestamp":"2023-07-01T04:35:25.542Z","count":0,"uniques":0},{"timestamp":"2023-08-01T04:35:25.542Z","count":0,"uniques":0},{"timestamp":"2023-09-01T04:35:25.542Z","count":0,"uniques":0},{"timestamp":"2023-10-01T04:35:25.542Z","count":0,"uniques":0},{"timestamp":"2023-11-01T04:35:25.542Z","count":0,"uniques":0},{"timestamp":"2023-12-01T04:35:25.542Z","count":0,"uniques":0},{"timestamp":"2024-01-01T04:35:25.542Z","count":0,"uniques":0},{"timestamp":"2024-02-01T04:35:25.542Z","count":0,"uniques":0},{"timestamp":"2024-03-01T04:35:25.542Z","count":0,"uniques":0},{"timestamp":"2024-04-01T04:35:25.542Z","count":0,"uniques":0},{"timestamp":"2024-05-01T12:15:23.914Z","count":98,"uniques":28},{"timestamp":"2024-06-01T12:14:03.697Z","count":106,"uniques":44}]
