[{"timestamp":"2025-05-13T00:46:11.649Z","count":0,"uniques":0},{"timestamp":"2025-05-14T00:45:59.516Z","count":0,"uniques":0},{"timestamp":"2025-05-15T00:45:27.410Z","count":0,"uniques":0},{"timestamp":"2025-05-16T00:46:49.295Z","count":0,"uniques":0},{"timestamp":"2025-05-17T00:45:00.056Z","count":0,"uniques":0},{"timestamp":"2025-05-18T00:51:08.619Z","count":0,"uniques":0},{"timestamp":"2025-05-19T00:50:00.868Z","count":0,"uniques":0},{"timestamp":"2025-05-20T00:47:29.608Z","count":0,"uniques":0}]
